pipecat_ai_cli-0.1.15.dist-info/licenses/LICENSE
pipecat_cli/__init__.py
pipecat_cli/main.py
pipecat_cli/commands/__init__.py
pipecat_cli/commands/init.py
pipecat_cli/generators/__init__.py
pipecat_cli/generators/project.py
pipecat_cli/prompts/__init__.py
pipecat_cli/prompts/questions.py
pipecat_cli/registry/__init__.py
pipecat_cli/registry/_configs.py
pipecat_cli/registry/_imports.py
pipecat_cli/registry/service_loader.py
pipecat_cli/registry/service_metadata.py
pipecat_cli/templates/README.md.jinja2
pipecat_cli/templates/gitignore.jinja2
pipecat_cli/templates/_readme_blocks/how_it_works_daily_pstn.jinja2
pipecat_cli/templates/_readme_blocks/how_it_works_twilio_daily_sip.jinja2
pipecat_cli/templates/_readme_blocks/project_structure_daily_pstn.jinja2
pipecat_cli/templates/_readme_blocks/project_structure_twilio_daily_sip.jinja2
pipecat_cli/templates/_readme_blocks/setup_daily_pstn.jinja2
pipecat_cli/templates/_readme_blocks/setup_telnyx.jinja2
pipecat_cli/templates/_readme_blocks/setup_twilio.jinja2
pipecat_cli/templates/_readme_blocks/setup_twilio_daily_sip.jinja2
pipecat_cli/templates/client/react-nextjs/.gitignore
pipecat_cli/templates/client/react-nextjs/env.example
pipecat_cli/templates/client/react-nextjs/eslint.config.mjs
pipecat_cli/templates/client/react-nextjs/next.config.ts
pipecat_cli/templates/client/react-nextjs/package.json.jinja2
pipecat_cli/templates/client/react-nextjs/postcss.config.mjs
pipecat_cli/templates/client/react-nextjs/tsconfig.json
pipecat_cli/templates/client/react-nextjs/public/pipecat.svg
pipecat_cli/templates/client/react-nextjs/src/config.ts.jinja2
pipecat_cli/templates/client/react-nextjs/src/app/globals.css
pipecat_cli/templates/client/react-nextjs/src/app/layout.tsx
pipecat_cli/templates/client/react-nextjs/src/app/page.tsx
pipecat_cli/templates/client/react-nextjs/src/app/api/sessions/[sessionId]/[...path]/route.ts
pipecat_cli/templates/client/react-nextjs/src/app/api/start/route.ts
pipecat_cli/templates/client/react-nextjs/src/app/components/App.tsx
pipecat_ai_cli-0.1.15.dist-info/METADATA
pipecat_ai_cli-0.1.15.dist-info/WHEEL
pipecat_ai_cli-0.1.15.dist-info/entry_points.txt
pipecat_ai_cli-0.1.15.dist-info/top_level.txt
pipecat_ai_cli-0.1.15.dist-info/RECORD
