Metadata-Version: 2.4
Name: pipecat-ai-cli
Version: 0.1.15
Summary: CLI for building, deploying, and monitoring Pipecat voice agents
License-Expression: BSD-2-Clause
Project-URL: Source, https://github.com/pipecat-ai/pipecat-cli
Project-URL: Website, https://pipecat.ai
Project-URL: Issues, https://github.com/pipecat-ai/pipecat-cli/issues
Keywords: pipecat,ai,cli,voice,agents,scaffolding
Classifier: Development Status :: 5 - Production/Stable
Classifier: Intended Audience :: Developers
Classifier: Programming Language :: Python :: 3
Classifier: Programming Language :: Python :: 3.10
Classifier: Programming Language :: Python :: 3.11
Classifier: Programming Language :: Python :: 3.12
Classifier: Programming Language :: Python :: 3.13
Classifier: Topic :: Software Development :: Code Generators
Classifier: Topic :: Software Development :: Libraries :: Python Modules
Classifier: Topic :: Multimedia :: Sound/Audio
Classifier: Topic :: Communications :: Conferencing
Requires-Python: >=3.10
License-File: LICENSE
Requires-Dist: typer<1,>=0.20.0
Requires-Dist: rich<14,>=13.0.0
Requires-Dist: jinja2<4,>=3.1.0
Requires-Dist: questionary<3,>=2.0.0
Requires-Dist: ruff<1,>=0.12.1
Requires-Dist: pipecatcloud>=0.2.16
Provides-Extra: tail
Requires-Dist: pipecat-ai-tail>=0.0.2; extra == "tail"
Dynamic: license-file
